[
  {
    "title": "Popeves Mega Sale",
    "image": "https://demandeals.com/img/banner/1769058971_e80e4535eac956dd225d.webp",
    "discount": "Huge Savings"
  },
  {
    "title": "Shyaway Big Days",
    "image": "https://demandeals.com/img/banner/1768968096_e66378033236edcd8418.webp",
    "discount": "Up to 75% Off"
  },
  {
    "title": "Indigo",
    "image": "https://demandeals.com/img/banner/1769067366_30db363c9632802edda2.webp",
    "discount": "Worth Maximum"
  },
  {
    "title": "Bank Offers",
    "image": "https://demandeals.com/img/topDeals/1768988463_d6f79c552f61adbb5740.webp",
    "discount": "Huge Savings"
  }
]
